[
   {
      "order": 0,
      "carPlate": "\u0e2a\u0e234321",
      "timeIn": "17/03/2022 00:53",
      "cost": 0,
      "status": 1
   },
   {
      "order": 0,
      "carPlate": "\u0e01\u0e011234",
      "timeIn": "17/03/2022 00:53",
      "cost": 0,
      "status": 1
   },
   {
      "order": 0,
      "carPlate": "\u0e01\u0e041234",
      "timeIn": "16/03/2022 22:26",
      "cost": 0,
      "status": 1
   },
   {
      "order": 1,
      "carPlate": "\u0e01\u0e071234",
      "timeIn": "16/03/2022 22:26",
      "cost": 0,
      "status": 1
   },
   {
      "order": 2,
      "carPlate": "\u0e01\u0e081234",
      "timeIn": "16/03/2022 22:26",
      "cost": 0,
      "status": 1
   },
   {
      "order": 0,
      "carPlate": "w",
      "timeIn": "16/03/2022 22:38",
      "cost": 0,
      "status": 1
   },
   {
      "order": 1,
      "carPlate": "q",
      "timeIn": "16/03/2022 22:38",
      "cost": 0,
      "status": 1
   },
   {
      "order": 0,
      "carPlate": "ddd",
      "timeIn": "16/03/2022 22:45",
      "cost": 0,
      "status": 1
   },
   {
      "order": 0,
      "carPlate": "\u0e01\u0e084444",
      "timeIn": "16/03/2022 23:56",
      "cost": 0,
      "status": 1
   },
   {
      "order": 1,
      "carPlate": "\u0e01\u0e2b3544",
      "timeIn": "00:00:19",
      "cost": 0,
      "status": 1
   },
   {
      "order": 0,
      "carPlate": "\u0e01\u0e141234",
      "timeIn": "17/03/2022 00:33",
      "cost": 0,
      "status": 1
   },
   {
      "order": 1,
      "carPlate": "\u0e09\u0e0a5889",
      "timeIn": "00:33:37",
      "cost": 0,
      "status": 1
   }
]