[
    {
        "order": 1,
        "carPlate": "222",
        "timeIn": "22:38:38",
        "cost": "1000",
        "shop": "shop2",
        "status": 0
    },
    {
        "order": 2,
        "carPlate": "222",
        "timeIn": "23:56:16",
        "cost": "3000",
        "shop": "PPShop",
        "status": 0
    },
    {
        "order": 3,
        "carPlate": "222",
        "timeIn": "23:59:02",
        "cost": "5000",
        "shop": "PPShop",
        "status": 0
    },
    {
        "order": 4,
        "carPlate": "333",
        "timeIn": "00:02:33",
        "cost": "2000",
        "shop": "ohmShop",
        "status": 0
    },
    {
        "order": 5,
        "carPlate": "333",
        "timeIn": "00:04:53",
        "cost": "800",
        "shop": "q123",
        "status": 0
    },
    {
        "order": 6,
        "carPlate": "222",
        "timeIn": "00:05:09",
        "cost": "500",
        "shop": "ohmShop",
        "status": 0
    },
    {
        "order": 7,
        "carPlate": "333",
        "timeIn": "00:05:21",
        "cost": "432",
        "shop": "q123",
        "status": 0
    },
    {
        "order": 8,
        "carPlate": "333",
        "timeIn": "00:05:49",
        "cost": "543",
        "shop": "q123",
        "status": 0
    },
    {
        "order": 9,
        "carPlate": "222",
        "timeIn": "00:05:49",
        "cost": "5000",
        "shop": "ohmShop",
        "status": 0
    },
    {
        "order": 10,
        "carPlate": "222",
        "timeIn": "00:06:03",
        "cost": "222",
        "shop": "q123",
        "status": 0
    },
    {
        "order": 11,
        "carPlate": "333",
        "timeIn": "00:09:31",
        "cost": "1000",
        "shop": "winshop",
        "status": 0
    },
    {
        "order": 12,
        "carPlate": "222",
        "timeIn": "00:09:43",
        "cost": "10000",
        "shop": "ohmShop",
        "status": 0
    },
    {
        "order": 13,
        "carPlate": "333",
        "timeIn": "00:10:01",
        "cost": "1",
        "shop": "winshop",
        "status": 0
    },
    {
        "order": 14,
        "carPlate": "333",
        "timeIn": "00:28:09",
        "cost": "1000",
        "shop": "1",
        "status": 0
    },
    {
        "order": 15,
        "carPlate": "222",
        "timeIn": "00:35:35",
        "cost": "13",
        "shop": "PPShop",
        "status": 0
    },
    {
        "order": 16,
        "carPlate": "222",
        "timeIn": "15:11:07",
        "cost": "11",
        "shop": "www",
        "status": 0
    },
    {
        "order": 17,
        "carPlate": "333",
        "timeIn": "15:15:17",
        "cost": "20",
        "shop": "W2",
        "status": 0
    },
    {
        "order": 18,
        "carPlate": "222",
        "timeIn": "15:49:13",
        "cost": "1000",
        "shop": "FoodSHOP1",
        "status": 0
    },
    {
        "order": 19,
        "carPlate": "333",
        "timeIn": "15:51:31",
        "cost": "5000",
        "shop": "FoodSHOP1",
        "status": 0
    },
    {
        "order": 20,
        "carPlate": "111",
        "timeIn": "16:06:39",
        "cost": "1222",
        "shop": "WWW",
        "status": 0
    }
]